<?xml version="1.0" encoding="UTF-8"?>
<stats>
	<hr>
	<batter>
		<jersey>0</jersey>
		<playername>Pesce, C</playername>
		<teamname></teamname>
		<ab>3</ab>
		<ab>3</ab>
		<runs>1</runs>
		<hits>2</hits>
		<bib>0</bib>
		<trib>0</trib>
		<hr>0</hr>
		<rbi>0</rbi>
		<bb>1</bb>
		<hp>0</hp>
		<so>0</so>
		<sf>0</sf>
		<sb>0</sb>
		<dp>0</dp>
		<obp>.750</obp>
		<slg>.667</slg>
		<avg>.667</avg>
	</batter>
	<batter>
		<jersey>7</jersey>
		<playername>munoz, s</playername>
		<teamname></teamname>
		<ab>2</ab>
		<ab>2</ab>
		<runs>3</runs>
		<hits>2</hits>
		<bib>0</bib>
		<trib>0</trib>
		<hr>0</hr>
		<rbi>1</rbi>
		<bb>1</bb>
		<hp>0</hp>
		<so>0</so>
		<sf>0</sf>
		<sb>0</sb>
		<dp>0</dp>
		<obp>1.000</obp>
		<slg>1.000</slg>
		<avg>1.000</avg>
	</batter>
	<batter>
		<jersey>8</jersey>
		<playername>smith, h</playername>
		<teamname></teamname>
		<ab>3</ab>
		<ab>3</ab>
		<runs>3</runs>
		<hits>2</hits>
		<bib>0</bib>
		<trib>0</trib>
		<hr>0</hr>
		<rbi>1</rbi>
		<bb>0</bb>
		<hp>0</hp>
		<so>0</so>
		<sf>0</sf>
		<sb>0</sb>
		<dp>0</dp>
		<obp>.667</obp>
		<slg>.667</slg>
		<avg>.667</avg>
	</batter>
	<batter>
		<jersey>9</jersey>
		<playername>cervasio, j</playername>
		<teamname></teamname>
		<ab>3</ab>
		<ab>3</ab>
		<runs>1</runs>
		<hits>2</hits>
		<bib>0</bib>
		<trib>0</trib>
		<hr>0</hr>
		<rbi>0</rbi>
		<bb>0</bb>
		<hp>0</hp>
		<so>0</so>
		<sf>0</sf>
		<sb>0</sb>
		<dp>0</dp>
		<obp>.667</obp>
		<slg>.667</slg>
		<avg>.667</avg>
	</batter>
	<batter>
		<jersey>6</jersey>
		<playername>broderick, b</playername>
		<teamname></teamname>
		<ab>2</ab>
		<ab>2</ab>
		<runs>2</runs>
		<hits>1</hits>
		<bib>0</bib>
		<trib>0</trib>
		<hr>0</hr>
		<rbi>0</rbi>
		<bb>1</bb>
		<hp>0</hp>
		<so>0</so>
		<sf>0</sf>
		<sb>0</sb>
		<dp>0</dp>
		<obp>.667</obp>
		<slg>.500</slg>
		<avg>.500</avg>
	</batter>
	<batter>
		<jersey>4</jersey>
		<playername>cuccinello, a</playername>
		<teamname></teamname>
		<ab>4</ab>
		<ab>4</ab>
		<runs>2</runs>
		<hits>2</hits>
		<bib>0</bib>
		<trib>2</trib>
		<hr>0</hr>
		<rbi>3</rbi>
		<bb>0</bb>
		<hp>0</hp>
		<so>0</so>
		<sf>0</sf>
		<sb>0</sb>
		<dp>0</dp>
		<obp>.500</obp>
		<slg>1.50</slg>
		<avg>.500</avg>
	</batter>
	<batter>
		<jersey>5</jersey>
		<playername>popowich, j</playername>
		<teamname></teamname>
		<ab>3</ab>
		<ab>3</ab>
		<runs>2</runs>
		<hits>2</hits>
		<bib>0</bib>
		<trib>0</trib>
		<hr>0</hr>
		<rbi>1</rbi>
		<bb>0</bb>
		<hp>0</hp>
		<so>0</so>
		<sf>0</sf>
		<sb>0</sb>
		<dp>0</dp>
		<obp>.667</obp>
		<slg>.667</slg>
		<avg>.667</avg>
	</batter>
	<batter>
		<jersey>1</jersey>
		<playername>Popowitch, J</playername>
		<teamname></teamname>
		<ab>3</ab>
		<ab>3</ab>
		<runs>2</runs>
		<hits>2</hits>
		<bib>0</bib>
		<trib>0</trib>
		<hr>0</hr>
		<rbi>3</rbi>
		<bb>1</bb>
		<hp>0</hp>
		<so>0</so>
		<sf>0</sf>
		<sb>0</sb>
		<dp>0</dp>
		<obp>.750</obp>
		<slg>.667</slg>
		<avg>.667</avg>
	</batter>
	<batter>
		<jersey>3</jersey>
		<playername>cuccinello, t</playername>
		<teamname></teamname>
		<ab>3</ab>
		<ab>3</ab>
		<runs>1</runs>
		<hits>2</hits>
		<bib>0</bib>
		<trib>0</trib>
		<hr>0</hr>
		<rbi>2</rbi>
		<bb>1</bb>
		<hp>0</hp>
		<so>0</so>
		<sf>0</sf>
		<sb>0</sb>
		<dp>0</dp>
		<obp>.750</obp>
		<slg>.667</slg>
		<avg>.667</avg>
	</batter>
	<batter>
		<jersey>10</jersey>
		<playername>jones, m</playername>
		<teamname></teamname>
		<ab>3</ab>
		<ab>3</ab>
		<runs>2</runs>
		<hits>2</hits>
		<bib>0</bib>
		<trib>0</trib>
		<hr>0</hr>
		<rbi>0</rbi>
		<bb>0</bb>
		<hp>0</hp>
		<so>0</so>
		<sf>0</sf>
		<sb>0</sb>
		<dp>0</dp>
		<obp>.667</obp>
		<slg>.667</slg>
		<avg>.667</avg>
	</batter>
	</hr>
	<avr>
	<batter>
		<jersey>7</jersey>
		<playername>munoz, s</playername>
		<teamname></teamname>
		<ab>2</ab>
		<ab>2</ab>
		<runs>3</runs>
		<hits>2</hits>
		<bib>0</bib>
		<trib>0</trib>
		<hr>0</hr>
		<rbi>1</rbi>
		<bb>1</bb>
		<hp>0</hp>
		<so>0</so>
		<sf>0</sf>
		<sb>0</sb>
		<dp>0</dp>
		<obp>1.000</obp>
		<slg>1.000</slg>
		<avg>1.000</avg>
	</batter>
	<batter>
		<jersey>8</jersey>
		<playername>smith, h</playername>
		<teamname></teamname>
		<ab>3</ab>
		<ab>3</ab>
		<runs>3</runs>
		<hits>2</hits>
		<bib>0</bib>
		<trib>0</trib>
		<hr>0</hr>
		<rbi>1</rbi>
		<bb>0</bb>
		<hp>0</hp>
		<so>0</so>
		<sf>0</sf>
		<sb>0</sb>
		<dp>0</dp>
		<obp>.667</obp>
		<slg>.667</slg>
		<avg>.667</avg>
	</batter>
	<batter>
		<jersey>9</jersey>
		<playername>cervasio, j</playername>
		<teamname></teamname>
		<ab>3</ab>
		<ab>3</ab>
		<runs>1</runs>
		<hits>2</hits>
		<bib>0</bib>
		<trib>0</trib>
		<hr>0</hr>
		<rbi>0</rbi>
		<bb>0</bb>
		<hp>0</hp>
		<so>0</so>
		<sf>0</sf>
		<sb>0</sb>
		<dp>0</dp>
		<obp>.667</obp>
		<slg>.667</slg>
		<avg>.667</avg>
	</batter>
	<batter>
		<jersey>0</jersey>
		<playername>Pesce, C</playername>
		<teamname></teamname>
		<ab>3</ab>
		<ab>3</ab>
		<runs>1</runs>
		<hits>2</hits>
		<bib>0</bib>
		<trib>0</trib>
		<hr>0</hr>
		<rbi>0</rbi>
		<bb>1</bb>
		<hp>0</hp>
		<so>0</so>
		<sf>0</sf>
		<sb>0</sb>
		<dp>0</dp>
		<obp>.750</obp>
		<slg>.667</slg>
		<avg>.667</avg>
	</batter>
	<batter>
		<jersey>10</jersey>
		<playername>jones, m</playername>
		<teamname></teamname>
		<ab>3</ab>
		<ab>3</ab>
		<runs>2</runs>
		<hits>2</hits>
		<bib>0</bib>
		<trib>0</trib>
		<hr>0</hr>
		<rbi>0</rbi>
		<bb>0</bb>
		<hp>0</hp>
		<so>0</so>
		<sf>0</sf>
		<sb>0</sb>
		<dp>0</dp>
		<obp>.667</obp>
		<slg>.667</slg>
		<avg>.667</avg>
	</batter>
	<batter>
		<jersey>3</jersey>
		<playername>cuccinello, t</playername>
		<teamname></teamname>
		<ab>3</ab>
		<ab>3</ab>
		<runs>1</runs>
		<hits>2</hits>
		<bib>0</bib>
		<trib>0</trib>
		<hr>0</hr>
		<rbi>2</rbi>
		<bb>1</bb>
		<hp>0</hp>
		<so>0</so>
		<sf>0</sf>
		<sb>0</sb>
		<dp>0</dp>
		<obp>.750</obp>
		<slg>.667</slg>
		<avg>.667</avg>
	</batter>
	<batter>
		<jersey>5</jersey>
		<playername>popowich, j</playername>
		<teamname></teamname>
		<ab>3</ab>
		<ab>3</ab>
		<runs>2</runs>
		<hits>2</hits>
		<bib>0</bib>
		<trib>0</trib>
		<hr>0</hr>
		<rbi>1</rbi>
		<bb>0</bb>
		<hp>0</hp>
		<so>0</so>
		<sf>0</sf>
		<sb>0</sb>
		<dp>0</dp>
		<obp>.667</obp>
		<slg>.667</slg>
		<avg>.667</avg>
	</batter>
	<batter>
		<jersey>1</jersey>
		<playername>Popowitch, J</playername>
		<teamname></teamname>
		<ab>3</ab>
		<ab>3</ab>
		<runs>2</runs>
		<hits>2</hits>
		<bib>0</bib>
		<trib>0</trib>
		<hr>0</hr>
		<rbi>3</rbi>
		<bb>1</bb>
		<hp>0</hp>
		<so>0</so>
		<sf>0</sf>
		<sb>0</sb>
		<dp>0</dp>
		<obp>.750</obp>
		<slg>.667</slg>
		<avg>.667</avg>
	</batter>
	<batter>
		<jersey>4</jersey>
		<playername>cuccinello, a</playername>
		<teamname></teamname>
		<ab>4</ab>
		<ab>4</ab>
		<runs>2</runs>
		<hits>2</hits>
		<bib>0</bib>
		<trib>2</trib>
		<hr>0</hr>
		<rbi>3</rbi>
		<bb>0</bb>
		<hp>0</hp>
		<so>0</so>
		<sf>0</sf>
		<sb>0</sb>
		<dp>0</dp>
		<obp>.500</obp>
		<slg>1.50</slg>
		<avg>.500</avg>
	</batter>
	<batter>
		<jersey>6</jersey>
		<playername>broderick, b</playername>
		<teamname></teamname>
		<ab>2</ab>
		<ab>2</ab>
		<runs>2</runs>
		<hits>1</hits>
		<bib>0</bib>
		<trib>0</trib>
		<hr>0</hr>
		<rbi>0</rbi>
		<bb>1</bb>
		<hp>0</hp>
		<so>0</so>
		<sf>0</sf>
		<sb>0</sb>
		<dp>0</dp>
		<obp>.667</obp>
		<slg>.500</slg>
		<avg>.500</avg>
	</batter>
	</avr>
	<rbi>
	<batter>
		<jersey>1</jersey>
		<playername>Popowitch, J</playername>
		<teamname></teamname>
		<ab>3</ab>
		<ab>3</ab>
		<runs>2</runs>
		<hits>2</hits>
		<bib>0</bib>
		<trib>0</trib>
		<hr>0</hr>
		<rbi>3</rbi>
		<bb>1</bb>
		<hp>0</hp>
		<so>0</so>
		<sf>0</sf>
		<sb>0</sb>
		<dp>0</dp>
		<obp>.750</obp>
		<slg>.667</slg>
		<avg>.667</avg>
	</batter>
	<batter>
		<jersey>4</jersey>
		<playername>cuccinello, a</playername>
		<teamname></teamname>
		<ab>4</ab>
		<ab>4</ab>
		<runs>2</runs>
		<hits>2</hits>
		<bib>0</bib>
		<trib>2</trib>
		<hr>0</hr>
		<rbi>3</rbi>
		<bb>0</bb>
		<hp>0</hp>
		<so>0</so>
		<sf>0</sf>
		<sb>0</sb>
		<dp>0</dp>
		<obp>.500</obp>
		<slg>1.50</slg>
		<avg>.500</avg>
	</batter>
	<batter>
		<jersey>3</jersey>
		<playername>cuccinello, t</playername>
		<teamname></teamname>
		<ab>3</ab>
		<ab>3</ab>
		<runs>1</runs>
		<hits>2</hits>
		<bib>0</bib>
		<trib>0</trib>
		<hr>0</hr>
		<rbi>2</rbi>
		<bb>1</bb>
		<hp>0</hp>
		<so>0</so>
		<sf>0</sf>
		<sb>0</sb>
		<dp>0</dp>
		<obp>.750</obp>
		<slg>.667</slg>
		<avg>.667</avg>
	</batter>
	<batter>
		<jersey>5</jersey>
		<playername>popowich, j</playername>
		<teamname></teamname>
		<ab>3</ab>
		<ab>3</ab>
		<runs>2</runs>
		<hits>2</hits>
		<bib>0</bib>
		<trib>0</trib>
		<hr>0</hr>
		<rbi>1</rbi>
		<bb>0</bb>
		<hp>0</hp>
		<so>0</so>
		<sf>0</sf>
		<sb>0</sb>
		<dp>0</dp>
		<obp>.667</obp>
		<slg>.667</slg>
		<avg>.667</avg>
	</batter>
	<batter>
		<jersey>7</jersey>
		<playername>munoz, s</playername>
		<teamname></teamname>
		<ab>2</ab>
		<ab>2</ab>
		<runs>3</runs>
		<hits>2</hits>
		<bib>0</bib>
		<trib>0</trib>
		<hr>0</hr>
		<rbi>1</rbi>
		<bb>1</bb>
		<hp>0</hp>
		<so>0</so>
		<sf>0</sf>
		<sb>0</sb>
		<dp>0</dp>
		<obp>1.000</obp>
		<slg>1.000</slg>
		<avg>1.000</avg>
	</batter>
	<batter>
		<jersey>8</jersey>
		<playername>smith, h</playername>
		<teamname></teamname>
		<ab>3</ab>
		<ab>3</ab>
		<runs>3</runs>
		<hits>2</hits>
		<bib>0</bib>
		<trib>0</trib>
		<hr>0</hr>
		<rbi>1</rbi>
		<bb>0</bb>
		<hp>0</hp>
		<so>0</so>
		<sf>0</sf>
		<sb>0</sb>
		<dp>0</dp>
		<obp>.667</obp>
		<slg>.667</slg>
		<avg>.667</avg>
	</batter>
	<batter>
		<jersey>6</jersey>
		<playername>broderick, b</playername>
		<teamname></teamname>
		<ab>2</ab>
		<ab>2</ab>
		<runs>2</runs>
		<hits>1</hits>
		<bib>0</bib>
		<trib>0</trib>
		<hr>0</hr>
		<rbi>0</rbi>
		<bb>1</bb>
		<hp>0</hp>
		<so>0</so>
		<sf>0</sf>
		<sb>0</sb>
		<dp>0</dp>
		<obp>.667</obp>
		<slg>.500</slg>
		<avg>.500</avg>
	</batter>
	<batter>
		<jersey>9</jersey>
		<playername>cervasio, j</playername>
		<teamname></teamname>
		<ab>3</ab>
		<ab>3</ab>
		<runs>1</runs>
		<hits>2</hits>
		<bib>0</bib>
		<trib>0</trib>
		<hr>0</hr>
		<rbi>0</rbi>
		<bb>0</bb>
		<hp>0</hp>
		<so>0</so>
		<sf>0</sf>
		<sb>0</sb>
		<dp>0</dp>
		<obp>.667</obp>
		<slg>.667</slg>
		<avg>.667</avg>
	</batter>
	<batter>
		<jersey>0</jersey>
		<playername>Pesce, C</playername>
		<teamname></teamname>
		<ab>3</ab>
		<ab>3</ab>
		<runs>1</runs>
		<hits>2</hits>
		<bib>0</bib>
		<trib>0</trib>
		<hr>0</hr>
		<rbi>0</rbi>
		<bb>1</bb>
		<hp>0</hp>
		<so>0</so>
		<sf>0</sf>
		<sb>0</sb>
		<dp>0</dp>
		<obp>.750</obp>
		<slg>.667</slg>
		<avg>.667</avg>
	</batter>
	<batter>
		<jersey>10</jersey>
		<playername>jones, m</playername>
		<teamname></teamname>
		<ab>3</ab>
		<ab>3</ab>
		<runs>2</runs>
		<hits>2</hits>
		<bib>0</bib>
		<trib>0</trib>
		<hr>0</hr>
		<rbi>0</rbi>
		<bb>0</bb>
		<hp>0</hp>
		<so>0</so>
		<sf>0</sf>
		<sb>0</sb>
		<dp>0</dp>
		<obp>.667</obp>
		<slg>.667</slg>
		<avg>.667</avg>
	</batter>
	</rbi>
</stats>
